{
  "_fv": 47,
  "_type": "recipe",
  "definition": {
    "recipeType": "Crafting",
    "recipeRetstackSize": 8,
    "group": "",
    "cookingBookCategory": "MISC",
    "xpReward": 0.0,
    "cookingTime": 200,
    "craftingBookCategory": "MISC",
    "recipeShapeless": false,
    "recipeSlots": [
      {
        "value": "Items.COPPER_INGOT"
      },
      {
        "value": "Blocks.IRON_BLOCK"
      },
      {
        "value": "Items.COPPER_INGOT"
      },
      {
        "value": "Items.IRON_NUGGET"
      },
      {
        "value": "Blocks.TNT"
      },
      {
        "value": "Items.IRON_NUGGET"
      },
      {
        "value": "Items.NETHERITE_INGOT"
      },
      {
        "value": "CUSTOM:SteelslugShell"
      },
      {
        "value": "Items.NETHERITE_INGOT"
      }
    ],
    "recipeReturnStack": {
      "value": "CUSTOM:M203SteelSlug"
    },
    "name": "m_23_steel_slug_round",
    "namespace": "mod"
  }
}